gameOfFifteen/__init__.py
gameOfFifteen/businessLogic.py
gameOfFifteen/direction.py
gameOfFifteen/gameframe.py
gameOfFifteen/gui.py
gameOfFifteen/statisticGUI.py
gameOfFifteen/statistics.py
gameOfFifteen/statusbar.py
gameOfFifteen/toolbar.py
gameOfFifteen-4.1.dist-info/METADATA
gameOfFifteen-4.1.dist-info/RECORD
gameOfFifteen-4.1.dist-info/WHEEL
gameOfFifteen-4.1.dist-info/top_level.txt
